README
setup.cfg
setup.py
skiplogic/__init__.py
skiplogic.egg-info/PKG-INFO
skiplogic.egg-info/SOURCES.txt
skiplogic.egg-info/dependency_links.txt
skiplogic.egg-info/top_level.txt