Metadata-Version: 1.0
Name: skiplogic
Version: 0.1.0
Summary: Skip Logic API wrapper
Home-page: https://www.skiplogic.io
Author: Scott Cruwys
Author-email: scott@skiplogic.io
License: UNKNOWN
Platform: UNKNOWN
